{
  "$schema": "http://json-schema.org/draft-04/schema#",
  "id": "urn:harja",
  "type": "array",
  "maxItems": 20000,
  "items": {
    "id": "urn:harja/reitti/0",
    "type": "object",
    "additionalProperties": false,
    "properties": {
      "reittipiste": {
        "id": "urn:harja/reitti/0/reittipiste",
        "type": "object",
        "additionalProperties": false,
        "required": [
          "aika",
          "koordinaatit"
        ],
        "properties": {
          "aika": {
            "id": "urn:harja/reitti/0/aika",
            "type": "string",
            "format": "date-time"
          },
          "koordinaatit": {
            "id": "urn:harja/reitti/0/koordinaattisijainti",
            "type": "object",
            "additionalProperties": false,
            "$ref": "koordinaattisijainti.schema.json"
          },
          "tehtavat": {
            "id": "urn:harja/reitti/0/tehtavat/",
            "type": "object",
            "additionalProperties": false,
            "$ref": "tehtavat.schema.json"
          },
          "materiaalit": {
            "id": "urn:harja/reitti/0/maarat/",
            "type": "object",
            "additionalProperties": false,
            "$ref": "materiaalit.schema.json"
          },
          "havainnot": {
            "id": "urn:harja/reitti/0/havainnot",
            "type": "object",
            "additionalProperties": false,
            "$ref": "havainnot.schema.json"
          },
          "mittaustulokset": {
            "id": "urn:harja/mittaustulokset",
            "type": "object",
            "additionalProperties": false,
            "required": [
              "mittaaja"
            ],
            "properties": {
              "mittaaja": {
                "id": "urn:harja/mittaustulokset/mittaaja",
                "type": "string"
              },
              "talvihoito": {
                "id": "urn:harja/mittaustulokset/talvihoito",
                "type": "object",
                "additionalProperties": false,
                "required": [
                  "hoitoluokka",
                  "lumisuus",
                  "tasaisuus",
                  "kitka",
                  "lampotila",
                  "laatuvirheet"
                ],
                "properties": {
                  "hoitoluokka": {
                    "id": "urn:harja/mittaustulokset/talvihoito/hoitoluokka",
                    "type": "integer"
                  },
                  "lumisuus": {
                    "id": "urn:harja/mittaustulokset/talvihoito/lumisuus",
                    "type": "number"
                  },
                  "tasaisuus": {
                    "id": "urn:harja/mittaustulokset/talvihoito/tasaisuus",
                    "type": "number"
                  },
                  "kitka": {
                    "id": "urn:harja/mittaustulokset/talvihoito/kitka",
                    "type": "number"
                  },
                  "lampotila": {
                    "id": "urn:harja/mittaustulokset/talvihoito/lampotila",
                    "type": "number"
                  },
                  "laatuvirheet": {
                    "id": "urn:harja/mittaustulokset/talvihoito/laatuvirheet",
                    "type": "object",
                    "additionalProperties": false,
                    "required": [
                      "liukkaus",
                      "lumisuus",
                      "tasaisuus"
                    ],
                    "properties": {
                      "liukkaus": {
                        "id": "urn:harja/mittaustulokset/talvihoito/laatuvirheet/liukkaus",
                        "type": "boolean"
                      },
                      "lumisuus": {
                        "id": "urn:harja/mittaustulokset/talvihoito/laatuvirheet/lumisuus",
                        "type": "boolean"
                      },
                      "tasaisuus": {
                        "id": "urn:harja/mittaustulokset/talvihoito/laatuvirheet/tasaisuus",
                        "type": "boolean"
                      }
                    }
                  }
                }
              },
              "soratie": {
                "id": "urn:harja/soratie",
                "type": "object",
                "required": [
                  "hoitoluokka",
                  "tasaisuus",
                  "kiinteys",
                  "polyavuus",
                  "sivukaltevuus"
                ],
                "properties": {
                  "hoitoluokka": {
                    "id": "urn:harja/soratie/hoitoluokka",
                    "type": "integer",
                    "minimum": 1,
                    "maximum": 2
                  },
                  "tasaisuus": {
                    "id": "urn:harja/soratie/tasaisuus",
                    "type": "integer",
                    "minimum": 1,
                    "maximum": 5
                  },
                  "kiinteys": {
                    "id": "urn:harja/soratie/kiinteys",
                    "type": "integer",
                    "minimum": 1,
                    "maximum": 5
                  },
                  "polyavuus": {
                    "id": "urn:harja/soratie/polyavuus",
                    "type": "integer",
                    "minimum": 1,
                    "maximum": 5
                  },
                  "sivukaltevuus": {
                    "id": "urn:harja/soratie/sivukaltevuus",
                    "type": "number"
                  }
                }
              }
            }
          }
        }
      }
    }
  }
}